dumbwebsearch/__init__.py
dumbwebsearch/browse.py
dumbwebsearch/index.py
dumbwebsearch-0.2.0.dist-info/METADATA
dumbwebsearch-0.2.0.dist-info/WHEEL
dumbwebsearch-0.2.0.dist-info/entry_points.txt
dumbwebsearch-0.2.0.dist-info/RECORD
